pymoupostracker/__init__.py
pymoupostracker/pymoupostracker.py
pymoupostracker-0.2.0.dist-info/licenses/LICENSE.txt
pymoupostracker-0.2.0.dist-info/METADATA
pymoupostracker-0.2.0.dist-info/WHEEL
pymoupostracker-0.2.0.dist-info/top_level.txt
pymoupostracker-0.2.0.dist-info/RECORD
